README.rst
setup.py
sphinx_pypi_upload.py
Sphinx_PyPI_upload_2.egg-info/PKG-INFO
Sphinx_PyPI_upload_2.egg-info/SOURCES.txt
Sphinx_PyPI_upload_2.egg-info/dependency_links.txt
Sphinx_PyPI_upload_2.egg-info/entry_points.txt
Sphinx_PyPI_upload_2.egg-info/pbr.json
Sphinx_PyPI_upload_2.egg-info/top_level.txt