Metadata-Version: 1.1
Name: Sphinx-PyPI-upload-2
Version: 0.2.2
Summary: Setuptools command for uploading Sphinx documentation to the PyPI
Home-page: https://github.com/WoLpH/sphinx-pypi-upload
Author: Rick van Hattem
Author-email: wolph@wol.ph
License: BSD
Platform: any
Classifier: Topic :: Documentation
Classifier: Framework :: Setuptools Plugin
Classifier: Development Status :: 5 - Production/Stable
Classifier: Programming Language :: Python
Classifier: Intended Audience :: Developers
Classifier: Operating System :: OS Independent
Classifier: License :: OSI Approved :: BSD License
Classifier: Topic :: Software Development :: Documentation
Classifier: Topic :: Software Development :: Libraries :: Python Modules
